{"inkVersion":19,"root":[["^Practice","\n","^by","\n","^Trevor Hedgpeth","\n","ev","str","^Begin","/str","/ev",{"*":"0.c-0","flg":20},{"c-0":["^ ",{"->":"FirstDialog"},"\n",{"->":"0.g-0"},{"#f":5}],"g-0":["done",{"#f":5}]}],"done",{"FirstDialog":[["^Once upon a time noel and his freind Austin were bitches","\n","^These bitches be crazy","\n","ev","str","^They really do be","/str","/ev",{"*":".^.c-0","flg":20},"ev","str","^bitches dont be that crazy","/str","/ev",{"*":".^.c-1","flg":20},{"c-0":["^ \"You right cuz..\" ",{"->":"TheyCrazy"},"\n",{"#f":5}],"c-1":["^ \"You trippin cuz..\" ",{"->":"TheyAint"},"\n",{"#f":5}]}],{"#f":1}],"TheyCrazy":["^Bitches be trippin","\n","end",{"#f":1}],"TheyAint":["^You wrong fa dat ","end","\n","end",{"#f":1}],"#f":1}],"listDefs":{}}